{
  "__resolveType": "site/sections/Hero.tsx",
  "ctaActive": false,
  "title": "<p></p>",
  "subtitle": null,
  "backgroundImage": {
    "__resolveType": "website/flags/multivariate/image.ts",
    "variants": [
      {
        "value": "https://deco-sites-assets.s3.sa-east-1.amazonaws.com/issacar/7a0811bf-7fc1-4fed-ba4a-f4d34e3632f5/bannerdesk.jpeg",
        "rule": {
          "__resolveType": "website/matchers/device.ts",
          "desktop": true
        }
      },
      {
        "value": "https://deco-sites-assets.s3.sa-east-1.amazonaws.com/issacar/69f8034e-8374-4534-bed4-7a28c21bd5fe/mobilebbanner.jpeg",
        "rule": {
          "__resolveType": "website/matchers/device.ts",
          "desktop": false,
          "tablet": true,
          "mobile": true
        }
      }
    ]
  }
}